{"_type":"export","__export_format":4,"__export_date":"2023-11-13T03:52:39.053Z","__export_source":"insomnia.desktop.app:v8.4.0","resources":[{"_id":"req_85e8533b57754741af5a1d6e2313c734","parentId":"fld_a356e9f7204742c79ffb83fd086f559f","modified":1699817934582,"created":1698260575188,"url":"{{ _.baseURL }}/users","name":"Incluir","description":"","method":"POST","body":{"mimeType":"application/x-www-form-urlencoded","params":[{"id":"pair_5a8f2269e0d04479b50fcce51e760aac","name":"name","value":"Eduardo José","description":""},{"id":"pair_9ad5e7f5cdfc42bf8d09292231a94080","name":"email","value":"ejssantos@hotmail.com","description":""},{"id":"pair_62666c1b58cb4fb081fd57f466d485fd","name":"password","value":"123456","description":""}]},"parameters":[],"headers":[{"name":"Content-Type","value":"application/x-www-form-urlencoded"},{"name":"User-Agent","value":"insomnia/8.3.0"}],"authentication":{},"metaSortKey":-1699817394279,"isPrivate":false,"settingStoreCookies":true,"settingSendCookies":true,"settingDisableRenderRequestBody":false,"settingEncodeUrl":true,"settingRebuildPath":true,"settingFollowRedirects":"global","_type":"request"},{"_id":"fld_a356e9f7204742c79ffb83fd086f559f","parentId":"wrk_5ab5cb4d96934b778200c5ecaa078b75","modified":1699817384863,"created":1699817384863,"name":"Users","description":"","environment":{},"environmentPropertyOrder":null,"metaSortKey":-1699817384863,"_type":"request_group"},{"_id":"wrk_5ab5cb4d96934b778200c5ecaa078b75","parentId":null,"modified":1698281942059,"created":1698281942059,"name":"users-api","description":"","scope":"collection","_type":"workspace"},{"_id":"req_30e82a8aae2646e19073795a16eced66","parentId":"fld_a356e9f7204742c79ffb83fd086f559f","modified":1699825004328,"created":1698264858837,"url":"{{ _.baseURL }}/users","name":"Listar","description":"","method":"GET","body":{"mimeType":"application/x-www-form-urlencoded","params":[]},"parameters":[],"headers":[{"name":"Content-Type","value":"application/x-www-form-urlencoded"},{"name":"User-Agent","value":"insomnia/8.3.0"}],"authentication":{},"metaSortKey":-1699817394179,"isPrivate":false,"settingStoreCookies":true,"settingSendCookies":true,"settingDisableRenderRequestBody":false,"settingEncodeUrl":true,"settingRebuildPath":true,"settingFollowRedirects":"global","_type":"request"},{"_id":"req_e4c4fb3a960c4733a469610dcf543ee1","parentId":"fld_a356e9f7204742c79ffb83fd086f559f","modified":1699817406113,"created":1698264876046,"url":"{{ _.baseURL }}/users/1","name":"Buscar","description":"","method":"GET","body":{},"parameters":[],"headers":[{"name":"id","value":"1","id":"pair_63bb376c7c314c7ebe27a167242e567e"}],"authentication":{},"metaSortKey":-1699817394079,"isPrivate":false,"settingStoreCookies":true,"settingSendCookies":true,"settingDisableRenderRequestBody":false,"settingEncodeUrl":true,"settingRebuildPath":true,"settingFollowRedirects":"global","_type":"request"},{"_id":"req_300234bc11fc42dba91d81d293b7afff","parentId":"fld_a356e9f7204742c79ffb83fd086f559f","modified":1699817413446,"created":1698267928483,"url":"{{ _.baseURL }}/users/1","name":"Alterar","description":"","method":"PUT","body":{"mimeType":"application/x-www-form-urlencoded","params":[{"id":"pair_cb0d9aaec5e54c1bb8f0370dee1bf4f5","name":"name","value":"Eduardo José","description":""},{"id":"pair_34ce7d9d70d34c58b5d8367e1ccf802b","name":"email","value":"ejssantos@hotmail.com","description":""}]},"parameters":[],"headers":[{"name":"Content-Type","value":"application/x-www-form-urlencoded"},{"name":"User-Agent","value":"insomnia/8.3.0"}],"authentication":{},"metaSortKey":-1699817393979,"isPrivate":false,"settingStoreCookies":true,"settingSendCookies":true,"settingDisableRenderRequestBody":false,"settingEncodeUrl":true,"settingRebuildPath":true,"settingFollowRedirects":"global","_type":"request"},{"_id":"req_528c2f3f51424a6a9292c36dae7e6e65","parentId":"fld_a356e9f7204742c79ffb83fd086f559f","modified":1699817422683,"created":1698268122822,"url":"{{ _.baseURL }}/users/1","name":"Alterar Parcial","description":"","method":"PATCH","body":{"mimeType":"application/x-www-form-urlencoded","params":[{"id":"pair_c38e4ca7d0b142919ffc21c6063527a2","name":"name","value":"Eduardo José","description":""},{"id":"pair_8504e5c0089c4463b1203dd7620fb89b","name":"email","value":"ejssantos@hotmail.com","description":""}]},"parameters":[],"headers":[{"name":"Content-Type","value":"application/x-www-form-urlencoded"},{"name":"User-Agent","value":"insomnia/8.3.0"}],"authentication":{},"metaSortKey":-1699817393879,"isPrivate":false,"settingStoreCookies":true,"settingSendCookies":true,"settingDisableRenderRequestBody":false,"settingEncodeUrl":true,"settingRebuildPath":true,"settingFollowRedirects":"global","_type":"request"},{"_id":"req_4f9fdd34aef145f0a1371e59ff88fedf","parentId":"fld_a356e9f7204742c79ffb83fd086f559f","modified":1699817424766,"created":1698282564341,"url":"{{ _.baseURL }}/users/1","name":"Excluir","description":"","method":"DELETE","body":{},"parameters":[],"headers":[{"name":"User-Agent","value":"insomnia/8.3.0"}],"authentication":{},"metaSortKey":-1699817393779,"isPrivate":false,"settingStoreCookies":true,"settingSendCookies":true,"settingDisableRenderRequestBody":false,"settingEncodeUrl":true,"settingRebuildPath":true,"settingFollowRedirects":"global","_type":"request"},{"_id":"req_0314c01278ae406a9dd35f614f2e5976","parentId":"fld_a578df76693344d1abc2db86c9169933","modified":1699828210622,"created":1699818010157,"url":"{{ _.baseURL }}/auth/register","name":"Register","description":"","method":"POST","body":{"mimeType":"application/x-www-form-urlencoded","params":[{"id":"pair_5a8f2269e0d04479b50fcce51e760aac","name":"name","value":"Eduardo José","description":""},{"id":"pair_9ad5e7f5cdfc42bf8d09292231a94080","name":"email","value":"ejssantos@hotmail.com","description":""},{"id":"pair_62666c1b58cb4fb081fd57f466d485fd","name":"password","value":"123456","description":""}]},"parameters":[],"headers":[{"name":"Content-Type","value":"application/x-www-form-urlencoded"},{"name":"User-Agent","value":"insomnia/8.3.0"}],"authentication":{},"metaSortKey":-1699817462457,"isPrivate":false,"settingStoreCookies":true,"settingSendCookies":true,"settingDisableRenderRequestBody":false,"settingEncodeUrl":true,"settingRebuildPath":true,"settingFollowRedirects":"global","_type":"request"},{"_id":"fld_a578df76693344d1abc2db86c9169933","parentId":"wrk_5ab5cb4d96934b778200c5ecaa078b75","modified":1699817373319,"created":1699817373319,"name":"Auth","description":"","environment":{},"environmentPropertyOrder":null,"metaSortKey":-1699817373319,"_type":"request_group"},{"_id":"req_1f1fb5d84a3849649aa79aecdf6c5ddb","parentId":"fld_a578df76693344d1abc2db86c9169933","modified":1699818276293,"created":1699818089466,"url":"{{ _.baseURL }}/auth/forget","name":"Forget","description":"","method":"POST","body":{"mimeType":"application/x-www-form-urlencoded","params":[{"id":"pair_9ad5e7f5cdfc42bf8d09292231a94080","name":"email","value":"ejssantos@hotmail.com","description":""}]},"parameters":[],"headers":[{"name":"Content-Type","value":"application/x-www-form-urlencoded"},{"name":"User-Agent","value":"insomnia/8.3.0"}],"authentication":{},"metaSortKey":-1699817462257,"isPrivate":false,"settingStoreCookies":true,"settingSendCookies":true,"settingDisableRenderRequestBody":false,"settingEncodeUrl":true,"settingRebuildPath":true,"settingFollowRedirects":"global","_type":"request"},{"_id":"req_980d95e5667346c1af73285c7fc2163a","parentId":"fld_a578df76693344d1abc2db86c9169933","modified":1699847336130,"created":1699817459015,"url":"{{ _.baseURL }}/auth/login","name":"Login","description":"","method":"POST","body":{"mimeType":"application/x-www-form-urlencoded","params":[{"id":"pair_72bc83db47ed427da61608a5602bda5f","name":"email","value":"ejssantos@hotmail.com","description":""},{"id":"pair_80d0803fbba14c2da06b72ab9bd8682a","name":"password","value":"123456","description":""}]},"parameters":[],"headers":[{"name":"Content-Type","value":"application/x-www-form-urlencoded"},{"name":"User-Agent","value":"insomnia/8.3.0"}],"authentication":{},"metaSortKey":-1699817462157,"isPrivate":false,"settingStoreCookies":true,"settingSendCookies":true,"settingDisableRenderRequestBody":false,"settingEncodeUrl":true,"settingRebuildPath":true,"settingFollowRedirects":"global","_type":"request"},{"_id":"req_5879c8c3618b4b9987735b4ab4464b49","parentId":"fld_a578df76693344d1abc2db86c9169933","modified":1699828208525,"created":1699818337979,"url":"{{ _.baseURL }}/auth/reset","name":"Reset","description":"","method":"POST","body":{"mimeType":"application/x-www-form-urlencoded","params":[{"id":"pair_72bc83db47ed427da61608a5602bda5f","name":"email","value":"ejssantos@hotmail.com","description":""},{"id":"pair_80d0803fbba14c2da06b72ab9bd8682a","name":"token","value":"123456.458796","description":""}]},"parameters":[],"headers":[{"name":"Content-Type","value":"application/x-www-form-urlencoded"},{"name":"User-Agent","value":"insomnia/8.3.0"}],"authentication":{},"metaSortKey":-1699817428218,"isPrivate":false,"settingStoreCookies":true,"settingSendCookies":true,"settingDisableRenderRequestBody":false,"settingEncodeUrl":true,"settingRebuildPath":true,"settingFollowRedirects":"global","_type":"request"},{"_id":"req_7290fe6dcf6b40ec81cb0602784b398e","parentId":"fld_a578df76693344d1abc2db86c9169933","modified":1699847384869,"created":1699828181738,"url":"{{ _.baseURL }}/auth/check","name":"Check","description":"","method":"POST","body":{"mimeType":"application/x-www-form-urlencoded","params":[{"id":"pair_6d891fafe1c34f11ad638dc2f588f38e","name":"token","value":"{{ _.token }}","description":"","disabled":true}]},"parameters":[],"headers":[{"name":"Content-Type","value":"application/x-www-form-urlencoded","id":"pair_3cddf9421d784fd88ddff01290fedec6","disabled":false},{"name":"User-Agent","value":"insomnia/8.4.0","id":"pair_0ef554e3fb0a4217bf62dfaa65d420b3","disabled":false},{"id":"pair_6391c262c552445986a4ffba9503de28","name":"Authorization","value":"{{ _.token }}","description":"","disabled":true}],"authentication":{"type":"bearer","token":"{{ _.token }}","disabled":false},"metaSortKey":-1699817428118,"isPrivate":false,"settingStoreCookies":true,"settingSendCookies":true,"settingDisableRenderRequestBody":false,"settingEncodeUrl":true,"settingRebuildPath":true,"settingFollowRedirects":"global","_type":"request"},{"_id":"env_a36f4e7d96ab437684802d5e940c958a","parentId":"wrk_5ab5cb4d96934b778200c5ecaa078b75","modified":1698260197164,"created":1698260197164,"name":"Base Environment","data":{},"dataPropertyOrder":null,"color":null,"isPrivate":false,"metaSortKey":1698260197164,"_type":"environment"},{"_id":"jar_1cb6eb19209340aa89a7b647a05c43f8","parentId":"wrk_5ab5cb4d96934b778200c5ecaa078b75","modified":1698260197166,"created":1698260197166,"name":"Default Jar","cookies":[],"_type":"cookie_jar"},{"_id":"env_c3f6bf034bb44550ab106cec96486dac","parentId":"env_a36f4e7d96ab437684802d5e940c958a","modified":1699847442713,"created":1698260451296,"name":"Dev","data":{"baseURL":"http://localhost:3000","token":"eyJhbGciOiJIUzI1NiIsInR5cCI6IkpXVCJ9.eyJpZCI6MSwibmFtZSI6IkVkdWFyZG8gSm9zw6kiLCJlbWFpbCI6ImVqc3NhbnRvc0Bob3RtYWlsLmNvbSIsImlhdCI6MTY5OTg0NzQyNywibmJmIjoxNjk5ODQ3NDU3LCJleHAiOjE2OTk4NDc0ODcsImF1ZCI6InVzZXJzIiwiaXNzIjoibG9naW4iLCJzdWIiOiIxIn0.fPEsrJAMsY23tM4ObOdD_zA-otG5vrtcU5R4zixVu7I"},"dataPropertyOrder":{"&":["baseURL","token"]},"color":"#15f505","isPrivate":false,"metaSortKey":1698260451296,"_type":"environment"}]}